pyupm/__init__.py
pyupm/upm.py
pyupm-0.0.1.dist-info/licenses/LICENSE
pyupm-0.0.1.dist-info/METADATA
pyupm-0.0.1.dist-info/WHEEL
pyupm-0.0.1.dist-info/top_level.txt
pyupm-0.0.1.dist-info/RECORD
