Metadata-Version: 2.4
Name: pyupm
Version: 0.0.1
Summary: A simple code for Uncertainty Projected Mapping
Author-email: Anirban Chakraborty <anirban1990@gmail.com>, Srushti Rashmi Shirish <srushtirs@gmail.com>
License: MIT
Project-URL: Homepage, https://github.com/anirban1990/PyUPM
Requires-Python: ==3.9.18
License-File: LICENSE
Requires-Dist: pymc==5.6.0
Dynamic: license-file
